openai_toolbox/__init__.py
openai_toolbox/webhook_handler.py
openai_toolbox-0.0.3.dist-info/METADATA
openai_toolbox-0.0.3.dist-info/WHEEL
openai_toolbox-0.0.3.dist-info/licenses/LICENSE
openai_toolbox-0.0.3.dist-info/RECORD
