Metadata-Version: 2.1
Name: openai_toolbox
Version: 0.0.3
Summary: Usefull functionality for working with openai
Author-email: Justin Haenel <jhaenel10@gmail.com>
License: Copyright (c) 2018 The Python Packaging Authority
License-File: LICENSE
Classifier: License :: OSI Approved :: MIT License
Classifier: Operating System :: OS Independent
Classifier: Programming Language :: Python :: 3
Requires-Python: >=3.7
